pyfolio/__init__.py
pyfolio/_version.py
pyfolio/capacity.py
pyfolio/deprecate.py
pyfolio/interesting_periods.py
pyfolio/ipycompat.py
pyfolio/perf_attrib.py
pyfolio/plotting.py
pyfolio/pos.py
pyfolio/round_trips.py
pyfolio/tears.py
pyfolio/timeseries.py
pyfolio/txn.py
pyfolio/utils.py
pyfolio/examples/results.pickle
pyfolio/examples/round_trip_tear_sheet_example.ipynb
pyfolio/examples/sector_mappings_example.ipynb
pyfolio/examples/single_stock_example.ipynb
pyfolio/examples/slippage_example.ipynb
pyfolio/examples/zipline_algo_example.ipynb
pyfolio_reloaded-0.9.8.dist-info/LICENSE
pyfolio_reloaded-0.9.8.dist-info/METADATA
pyfolio_reloaded-0.9.8.dist-info/WHEEL
pyfolio_reloaded-0.9.8.dist-info/top_level.txt
pyfolio_reloaded-0.9.8.dist-info/RECORD
